{
  "openapi": "3.0.1",
  "info": {
    "title": "API",
    "version": "1.0"
  },
  "paths": {
    "/HubService/GetMembers/{groupName}": {
      "get": {
        "tags": [
          "HubService"
        ],
        "parameters": [
          {
            "name": "groupName",
            "in": "path",
            "required": true,
            "schema": {
              "type": "string"
            }
          }
        ],
        "responses": {
          "200": {
            "description": "OK"
          }
        }
      }
    },
    "/HubService/availableGroups": {
      "get": {
        "tags": [
          "HubService"
        ],
        "responses": {
          "200": {
            "description": "OK"
          }
        }
      }
    },
    "/HubService/GetUserGroupName/{connectionId}": {
      "get": {
        "tags": [
          "HubService"
        ],
        "parameters": [
          {
            "name": "connectionId",
            "in": "path",
            "required": true,
            "schema": {
              "type": "string"
            }
          }
        ],
        "responses": {
          "200": {
            "description": "OK"
          }
        }
      }
    }
  },
  "components": { }
}